{
  "1": {
    "article_id": "1",
    "incident_id": "4",
    "title": "How to Handle API Unavailable",
    "article_type": "resolution_steps",
    "created_by_id": "93",
    "reviewed_by_id": "74",
    "category": "api_integration",
    "view_count": 260,
    "status": "draft",
    "created_at": "2023-11-04T23:15:45.329018",
    "updated_at": "2025-04-27T21:27:18.206493"
  },
  "2": {
    "article_id": "2",
    "incident_id": "6",
    "title": "How to Handle API Connection Failed",
    "article_type": "faq",
    "created_by_id": "104",
    "reviewed_by_id": null,
    "category": "api_integration",
    "view_count": 329,
    "status": "published",
    "created_at": "2023-09-19T02:32:35.296572",
    "updated_at": "2024-08-11T19:48:40.782462"
  },
  "3": {
    "article_id": "3",
    "incident_id": "9",
    "title": "How to Handle OAuth Token Rejected",
    "article_type": "resolution_steps",
    "created_by_id": "11",
    "reviewed_by_id": null,
    "category": "api_integration",
    "view_count": 206,
    "status": "draft",
    "created_at": "2025-03-19T06:02:14.197513",
    "updated_at": "2025-03-28T10:51:52.005421"
  },
  "4": {
    "article_id": "4",
    "incident_id": "10",
    "title": "How to Handle API Connection Failed",
    "article_type": "resolution_steps",
    "created_by_id": "104",
    "reviewed_by_id": "9",
    "category": "api_integration",
    "view_count": 315,
    "status": "draft",
    "created_at": "2024-06-08T08:31:37.335803",
    "updated_at": "2025-04-21T16:21:05.911196"
  },
  "5": {
    "article_id": "5",
    "incident_id": "13",
    "title": "How to Handle Indexing Queue Backlog",
    "article_type": "faq",
    "created_by_id": "112",
    "reviewed_by_id": "75",
    "category": "monitoring_alerts",
    "view_count": 133,
    "status": "archived",
    "created_at": "2024-03-04T09:39:33.906657",
    "updated_at": "2024-07-07T21:04:00.666516"
  },
  "6": {
    "article_id": "6",
    "incident_id": "16",
    "title": "How to Handle Dashboard Query Latency",
    "article_type": "resolution_steps",
    "created_by_id": "26",
    "reviewed_by_id": "116",
    "category": "monitoring_alerts",
    "view_count": 222,
    "status": "published",
    "created_at": "2024-01-31T23:42:38.760370",
    "updated_at": "2024-10-25T17:05:45.399348"
  },
  "7": {
    "article_id": "7",
    "incident_id": "17",
    "title": "How to Handle Alert Flood from Multiple Sources",
    "article_type": "faq",
    "created_by_id": "56",
    "reviewed_by_id": "84",
    "category": "monitoring_alerts",
    "view_count": 203,
    "status": "archived",
    "created_at": "2024-11-01T01:20:27.632433",
    "updated_at": "2025-02-12T12:02:50.706464"
  },
  "8": {
    "article_id": "8",
    "incident_id": "20",
    "title": "How to Handle Failover Did Not Trigger",
    "article_type": "troubleshooting",
    "created_by_id": "70",
    "reviewed_by_id": "62",
    "category": "database_issues",
    "view_count": 224,
    "status": "draft",
    "created_at": "2024-01-29T23:16:39.007552",
    "updated_at": "2025-07-10T18:43:46.823783"
  },
  "9": {
    "article_id": "9",
    "incident_id": "21",
    "title": "How to Handle Connection Pool Exhausted",
    "article_type": "troubleshooting",
    "created_by_id": "92",
    "reviewed_by_id": "110",
    "category": "database_issues",
    "view_count": 220,
    "status": "archived",
    "created_at": "2024-05-19T15:05:42.219595",
    "updated_at": "2024-12-17T12:06:29.942445"
  },
  "10": {
    "article_id": "10",
    "incident_id": "26",
    "title": "How to Handle High Decline Rates from Processor",
    "article_type": "faq",
    "created_by_id": "9",
    "reviewed_by_id": null,
    "category": "payment_processing",
    "view_count": 108,
    "status": "published",
    "created_at": "2024-07-09T10:20:41.023075",
    "updated_at": "2025-03-05T10:05:25.961242"
  },
  "11": {
    "article_id": "11",
    "incident_id": "30",
    "title": "How to Handle API Connection Failed",
    "article_type": "faq",
    "created_by_id": "28",
    "reviewed_by_id": "89",
    "category": "api_integration",
    "view_count": 412,
    "status": "archived",
    "created_at": "2024-05-21T04:49:33.357162",
    "updated_at": "2024-08-28T03:04:50.818815"
  },
  "12": {
    "article_id": "12",
    "incident_id": "31",
    "title": "How to Handle High API Latency Detected",
    "article_type": "faq",
    "created_by_id": "4",
    "reviewed_by_id": null,
    "category": "api_integration",
    "view_count": 66,
    "status": "archived",
    "created_at": "2024-08-07T18:25:33.263629",
    "updated_at": "2024-09-02T15:50:48.661117"
  },
  "13": {
    "article_id": "13",
    "incident_id": "32",
    "title": "How to Handle DNS Resolution Failure for API",
    "article_type": "resolution_steps",
    "created_by_id": "57",
    "reviewed_by_id": null,
    "category": "api_integration",
    "view_count": 458,
    "status": "published",
    "created_at": "2023-12-03T23:39:38.734775",
    "updated_at": "2024-03-21T05:44:07.066853"
  },
  "14": {
    "article_id": "14",
    "incident_id": "36",
    "title": "How to Handle OAuth Token Rejected",
    "article_type": "resolution_steps",
    "created_by_id": "116",
    "reviewed_by_id": null,
    "category": "api_integration",
    "view_count": 8,
    "status": "published",
    "created_at": "2024-05-28T00:08:09.516097",
    "updated_at": "2024-09-14T10:04:08.957359"
  },
  "15": {
    "article_id": "15",
    "incident_id": "38",
    "title": "How to Handle DNS Resolution Failure for API",
    "article_type": "faq",
    "created_by_id": "12",
    "reviewed_by_id": "53",
    "category": "api_integration",
    "view_count": 161,
    "status": "archived",
    "created_at": "2024-09-15T16:22:11.199780",
    "updated_at": "2024-09-20T15:56:42.418230"
  },
  "16": {
    "article_id": "16",
    "incident_id": "39",
    "title": "How to Handle Webhook Delivery Failures",
    "article_type": "troubleshooting",
    "created_by_id": "30",
    "reviewed_by_id": "38",
    "category": "api_integration",
    "view_count": 283,
    "status": "published",
    "created_at": "2024-02-13T20:47:10.511869",
    "updated_at": "2025-08-11T09:45:19.659124"
  },
  "17": {
    "article_id": "17",
    "incident_id": "40",
    "title": "How to Handle DNS Resolution Failure for API",
    "article_type": "troubleshooting",
    "created_by_id": "93",
    "reviewed_by_id": "94",
    "category": "api_integration",
    "view_count": 463,
    "status": "published",
    "created_at": "2024-10-24T04:09:38.467470",
    "updated_at": "2025-05-14T15:05:28.991718"
  },
  "18": {
    "article_id": "18",
    "incident_id": "42",
    "title": "How to Handle Webhook Delivery Failures",
    "article_type": "resolution_steps",
    "created_by_id": "4",
    "reviewed_by_id": "114",
    "category": "api_integration",
    "view_count": 193,
    "status": "published",
    "created_at": "2024-06-10T15:52:19.839011",
    "updated_at": "2025-08-22T04:43:18.831908"
  },
  "19": {
    "article_id": "19",
    "incident_id": "43",
    "title": "How to Handle API Connection Failed",
    "article_type": "resolution_steps",
    "created_by_id": "43",
    "reviewed_by_id": null,
    "category": "api_integration",
    "view_count": 265,
    "status": "archived",
    "created_at": "2025-08-25T16:58:21.084966",
    "updated_at": "2025-08-31T00:32:17.034874"
  },
  "20": {
    "article_id": "20",
    "incident_id": "44",
    "title": "How to Handle Suspicious SSO Activity",
    "article_type": "troubleshooting",
    "created_by_id": "26",
    "reviewed_by_id": null,
    "category": "authentication_issues",
    "view_count": 340,
    "status": "published",
    "created_at": "2024-02-06T05:54:50.688448",
    "updated_at": "2025-02-27T13:35:48.030777"
  },
  "21": {
    "article_id": "21",
    "incident_id": "45",
    "title": "How to Handle Suspicious SSO Activity",
    "article_type": "faq",
    "created_by_id": "26",
    "reviewed_by_id": "71",
    "category": "authentication_issues",
    "view_count": 414,
    "status": "published",
    "created_at": "2024-08-21T12:28:43.379716",
    "updated_at": "2025-02-03T22:22:47.373697"
  },
  "22": {
    "article_id": "22",
    "incident_id": "46",
    "title": "How to Handle Brute Force Attempt Detected",
    "article_type": "resolution_steps",
    "created_by_id": "56",
    "reviewed_by_id": null,
    "category": "authentication_issues",
    "view_count": 418,
    "status": "archived",
    "created_at": "2024-04-19T05:26:11.926766",
    "updated_at": "2024-07-14T16:00:11.172988"
  },
  "23": {
    "article_id": "23",
    "incident_id": "48",
    "title": "How to Handle Token Expiry Mismatch",
    "article_type": "faq",
    "created_by_id": "12",
    "reviewed_by_id": null,
    "category": "authentication_issues",
    "view_count": 30,
    "status": "draft",
    "created_at": "2024-08-24T09:25:23.948408",
    "updated_at": "2025-06-08T20:55:03.554183"
  },
  "24": {
    "article_id": "24",
    "incident_id": "51",
    "title": "How to Handle Deadlocks Detected",
    "article_type": "resolution_steps",
    "created_by_id": "114",
    "reviewed_by_id": "112",
    "category": "database_issues",
    "view_count": 11,
    "status": "published",
    "created_at": "2024-03-28T09:38:17.676220",
    "updated_at": "2025-08-03T23:44:24.186677"
  },
  "25": {
    "article_id": "25",
    "incident_id": "52",
    "title": "How to Handle Replication Lag High",
    "article_type": "resolution_steps",
    "created_by_id": "104",
    "reviewed_by_id": "85",
    "category": "database_issues",
    "view_count": 343,
    "status": "archived",
    "created_at": "2025-02-22T01:56:40.085919",
    "updated_at": "2025-07-01T15:31:03.768791"
  },
  "26": {
    "article_id": "26",
    "incident_id": "56",
    "title": "How to Handle Replication Lag High",
    "article_type": "troubleshooting",
    "created_by_id": "23",
    "reviewed_by_id": "23",
    "category": "database_issues",
    "view_count": 249,
    "status": "archived",
    "created_at": "2024-09-21T14:13:53.623260",
    "updated_at": "2025-05-25T20:07:36.551149"
  },
  "27": {
    "article_id": "27",
    "incident_id": "57",
    "title": "How to Handle Deadlocks Detected",
    "article_type": "resolution_steps",
    "created_by_id": "4",
    "reviewed_by_id": null,
    "category": "database_issues",
    "view_count": 202,
    "status": "published",
    "created_at": "2025-07-31T23:09:02.503650",
    "updated_at": "2025-08-10T18:15:16.697815"
  },
  "28": {
    "article_id": "28",
    "incident_id": "59",
    "title": "How to Handle Replication Lag High",
    "article_type": "resolution_steps",
    "created_by_id": "106",
    "reviewed_by_id": "26",
    "category": "database_issues",
    "view_count": 481,
    "status": "published",
    "created_at": "2024-02-10T23:58:16.246324",
    "updated_at": "2024-02-29T22:52:06.866208"
  },
  "29": {
    "article_id": "29",
    "incident_id": "60",
    "title": "How to Handle Primary Database Unavailable",
    "article_type": "resolution_steps",
    "created_by_id": "95",
    "reviewed_by_id": "80",
    "category": "database_issues",
    "view_count": 92,
    "status": "published",
    "created_at": "2025-06-12T11:39:19.535479",
    "updated_at": "2025-06-21T04:00:35.830872"
  },
  "30": {
    "article_id": "30",
    "incident_id": "63",
    "title": "How to Handle Schema Migration Error",
    "article_type": "resolution_steps",
    "created_by_id": "72",
    "reviewed_by_id": null,
    "category": "database_issues",
    "view_count": 144,
    "status": "archived",
    "created_at": "2024-09-24T06:02:27.482341",
    "updated_at": "2024-10-14T19:20:00.403866"
  },
  "31": {
    "article_id": "31",
    "incident_id": "64",
    "title": "How to Handle Replication Lag High",
    "article_type": "resolution_steps",
    "created_by_id": "37",
    "reviewed_by_id": null,
    "category": "database_issues",
    "view_count": 209,
    "status": "archived",
    "created_at": "2024-02-22T06:06:58.150096",
    "updated_at": "2024-06-29T08:15:49.616702"
  },
  "32": {
    "article_id": "32",
    "incident_id": "65",
    "title": "How to Handle Deadlocks Detected",
    "article_type": "troubleshooting",
    "created_by_id": "70",
    "reviewed_by_id": "118",
    "category": "database_issues",
    "view_count": 66,
    "status": "archived",
    "created_at": "2025-03-16T15:11:45.171424",
    "updated_at": "2025-08-23T03:06:21.116592"
  },
  "33": {
    "article_id": "33",
    "incident_id": "67",
    "title": "How to Handle Primary Database Unavailable",
    "article_type": "troubleshooting",
    "created_by_id": "11",
    "reviewed_by_id": null,
    "category": "database_issues",
    "view_count": 250,
    "status": "archived",
    "created_at": "2024-04-09T06:42:32.026570",
    "updated_at": "2024-05-18T01:15:10.022154"
  },
  "34": {
    "article_id": "34",
    "incident_id": "68",
    "title": "How to Handle Write Conflicts Observed",
    "article_type": "faq",
    "created_by_id": "116",
    "reviewed_by_id": "116",
    "category": "database_issues",
    "view_count": 85,
    "status": "draft",
    "created_at": "2023-10-19T14:43:08.074163",
    "updated_at": "2024-02-22T14:36:23.557895"
  },
  "35": {
    "article_id": "35",
    "incident_id": "71",
    "title": "How to Handle OAuth Token Rejected",
    "article_type": "resolution_steps",
    "created_by_id": "9",
    "reviewed_by_id": "57",
    "category": "api_integration",
    "view_count": 163,
    "status": "published",
    "created_at": "2023-11-28T02:08:04.495510",
    "updated_at": "2024-01-07T08:13:52.034974"
  },
  "36": {
    "article_id": "36",
    "incident_id": "72",
    "title": "How to Handle High API Latency Detected",
    "article_type": "prevention_guide",
    "created_by_id": "85",
    "reviewed_by_id": null,
    "category": "api_integration",
    "view_count": 334,
    "status": "draft",
    "created_at": "2023-09-22T01:23:04.642537",
    "updated_at": "2024-03-03T14:05:37.572519"
  },
  "37": {
    "article_id": "37",
    "incident_id": "73",
    "title": "How to Handle OAuth Token Rejected",
    "article_type": "prevention_guide",
    "created_by_id": "93",
    "reviewed_by_id": null,
    "category": "api_integration",
    "view_count": 269,
    "status": "draft",
    "created_at": "2023-12-01T14:14:11.060405",
    "updated_at": "2025-01-13T01:37:04.727539"
  },
  "38": {
    "article_id": "38",
    "incident_id": "77",
    "title": "How to Handle Rate Limit Saturation",
    "article_type": "faq",
    "created_by_id": "9",
    "reviewed_by_id": null,
    "category": "api_integration",
    "view_count": 359,
    "status": "published",
    "created_at": "2024-05-24T04:49:26.150420",
    "updated_at": "2025-02-18T15:51:31.437472"
  },
  "39": {
    "article_id": "39",
    "incident_id": "78",
    "title": "How to Handle MFA Provider Timeout",
    "article_type": "faq",
    "created_by_id": "24",
    "reviewed_by_id": null,
    "category": "authentication_issues",
    "view_count": 310,
    "status": "published",
    "created_at": "2024-08-11T09:15:22.233667",
    "updated_at": "2025-08-27T10:34:58.810945"
  },
  "40": {
    "article_id": "40",
    "incident_id": "79",
    "title": "How to Handle Token Expiry Mismatch",
    "article_type": "resolution_steps",
    "created_by_id": "104",
    "reviewed_by_id": "117",
    "category": "authentication_issues",
    "view_count": 153,
    "status": "draft",
    "created_at": "2025-03-10T17:23:50.856277",
    "updated_at": "2025-07-05T22:57:49.126204"
  },
  "41": {
    "article_id": "41",
    "incident_id": "80",
    "title": "How to Handle SSO Login Failures",
    "article_type": "faq",
    "created_by_id": "25",
    "reviewed_by_id": "28",
    "category": "authentication_issues",
    "view_count": 258,
    "status": "archived",
    "created_at": "2024-05-11T23:07:40.060904",
    "updated_at": "2024-12-23T19:57:21.727833"
  },
  "42": {
    "article_id": "42",
    "incident_id": "82",
    "title": "How to Handle MFA Provider Timeout",
    "article_type": "resolution_steps",
    "created_by_id": "85",
    "reviewed_by_id": null,
    "category": "authentication_issues",
    "view_count": 77,
    "status": "draft",
    "created_at": "2025-03-07T02:06:42.563560",
    "updated_at": "2025-06-16T11:57:38.017172"
  },
  "43": {
    "article_id": "43",
    "incident_id": "84",
    "title": "How to Handle Multiple Failed Login Attempts",
    "article_type": "troubleshooting",
    "created_by_id": "43",
    "reviewed_by_id": "56",
    "category": "authentication_issues",
    "view_count": 22,
    "status": "draft",
    "created_at": "2023-11-07T03:37:21.485074",
    "updated_at": "2024-10-11T12:19:58.601822"
  },
  "44": {
    "article_id": "44",
    "incident_id": "85",
    "title": "How to Handle Multiple Failed Login Attempts",
    "article_type": "faq",
    "created_by_id": "56",
    "reviewed_by_id": "114",
    "category": "authentication_issues",
    "view_count": 257,
    "status": "draft",
    "created_at": "2024-07-05T20:44:35.127015",
    "updated_at": "2024-07-19T19:53:31.917124"
  },
  "45": {
    "article_id": "45",
    "incident_id": "87",
    "title": "How to Handle Multiple Failed Login Attempts",
    "article_type": "prevention_guide",
    "created_by_id": "23",
    "reviewed_by_id": "72",
    "category": "authentication_issues",
    "view_count": 307,
    "status": "archived",
    "created_at": "2024-05-06T09:41:17.096621",
    "updated_at": "2025-08-09T03:59:07.233329"
  },
  "46": {
    "article_id": "46",
    "incident_id": "91",
    "title": "How to Handle DNS Resolution Failure for API",
    "article_type": "resolution_steps",
    "created_by_id": "56",
    "reviewed_by_id": "35",
    "category": "api_integration",
    "view_count": 410,
    "status": "draft",
    "created_at": "2025-07-22T21:49:01.459665",
    "updated_at": "2025-08-05T03:39:01.512368"
  },
  "47": {
    "article_id": "47",
    "incident_id": "93",
    "title": "How to Handle Uneven Traffic Distribution",
    "article_type": "resolution_steps",
    "created_by_id": "70",
    "reviewed_by_id": "76",
    "category": "network_connectivity",
    "view_count": 271,
    "status": "published",
    "created_at": "2024-09-06T14:17:34.004328",
    "updated_at": "2025-06-27T14:30:32.909063"
  },
  "48": {
    "article_id": "48",
    "incident_id": "95",
    "title": "How to Handle VIP Not Reachable",
    "article_type": "faq",
    "created_by_id": "56",
    "reviewed_by_id": null,
    "category": "network_connectivity",
    "view_count": 391,
    "status": "published",
    "created_at": "2024-03-21T10:14:21.516612",
    "updated_at": "2025-06-05T23:05:23.002069"
  },
  "49": {
    "article_id": "49",
    "incident_id": "97",
    "title": "How to Handle Inbound Traffic Spike",
    "article_type": "prevention_guide",
    "created_by_id": "117",
    "reviewed_by_id": null,
    "category": "network_connectivity",
    "view_count": 309,
    "status": "draft",
    "created_at": "2024-12-19T03:44:23.701843",
    "updated_at": "2025-03-12T08:40:08.248384"
  },
  "50": {
    "article_id": "50",
    "incident_id": "99",
    "title": "How to Handle Unusual Port Scans Detected",
    "article_type": "faq",
    "created_by_id": "70",
    "reviewed_by_id": null,
    "category": "network_connectivity",
    "view_count": 70,
    "status": "archived",
    "created_at": "2023-11-27T21:20:24.255489",
    "updated_at": "2025-04-19T07:03:44.100687"
  },
  "51": {
    "article_id": "51",
    "incident_id": "102",
    "title": "How to Handle 5xx Error Spike on API",
    "article_type": "resolution_steps",
    "created_by_id": "39",
    "reviewed_by_id": "28",
    "category": "api_integration",
    "view_count": 202,
    "status": "draft",
    "created_at": "2024-10-11T08:05:29.721779",
    "updated_at": "2025-03-13T16:59:27.431783"
  },
  "52": {
    "article_id": "52",
    "incident_id": "103",
    "title": "How to Handle API Unavailable",
    "article_type": "resolution_steps",
    "created_by_id": "106",
    "reviewed_by_id": null,
    "category": "api_integration",
    "view_count": 486,
    "status": "archived",
    "created_at": "2024-05-11T15:41:18.616978",
    "updated_at": "2024-07-04T23:19:19.265588"
  },
  "53": {
    "article_id": "53",
    "incident_id": "104",
    "title": "How to Handle API Unavailable",
    "article_type": "resolution_steps",
    "created_by_id": "117",
    "reviewed_by_id": null,
    "category": "api_integration",
    "view_count": 46,
    "status": "archived",
    "created_at": "2024-09-08T20:46:41.741279",
    "updated_at": "2025-02-03T18:56:20.784936"
  },
  "54": {
    "article_id": "54",
    "incident_id": "106",
    "title": "How to Handle DNS Resolution Failure for API",
    "article_type": "resolution_steps",
    "created_by_id": "70",
    "reviewed_by_id": "66",
    "category": "api_integration",
    "view_count": 489,
    "status": "published",
    "created_at": "2023-09-09T07:50:50.205804",
    "updated_at": "2023-11-21T15:14:12.172925"
  },
  "55": {
    "article_id": "55",
    "incident_id": "108",
    "title": "How to Handle High API Latency Detected",
    "article_type": "troubleshooting",
    "created_by_id": "85",
    "reviewed_by_id": null,
    "category": "api_integration",
    "view_count": 108,
    "status": "published",
    "created_at": "2024-05-06T10:06:19.660158",
    "updated_at": "2025-02-05T12:38:53.267207"
  },
  "56": {
    "article_id": "56",
    "incident_id": "109",
    "title": "How to Handle High API Latency Detected",
    "article_type": "resolution_steps",
    "created_by_id": "38",
    "reviewed_by_id": null,
    "category": "api_integration",
    "view_count": 223,
    "status": "published",
    "created_at": "2023-12-28T16:12:53.953120",
    "updated_at": "2024-10-18T10:41:55.994309"
  },
  "57": {
    "article_id": "57",
    "incident_id": "110",
    "title": "How to Handle Intermittent Capture Failures",
    "article_type": "resolution_steps",
    "created_by_id": "32",
    "reviewed_by_id": "62",
    "category": "payment_processing",
    "view_count": 234,
    "status": "archived",
    "created_at": "2023-10-04T11:04:37.950902",
    "updated_at": "2023-10-25T22:23:02.449258"
  },
  "58": {
    "article_id": "58",
    "incident_id": "112",
    "title": "How to Handle Gateway Unreachable",
    "article_type": "troubleshooting",
    "created_by_id": "106",
    "reviewed_by_id": "25",
    "category": "payment_processing",
    "view_count": 34,
    "status": "draft",
    "created_at": "2025-07-17T22:56:29.305103",
    "updated_at": "2025-08-05T06:48:38.002503"
  },
  "59": {
    "article_id": "59",
    "incident_id": "113",
    "title": "How to Handle Gateway Timeout Errors",
    "article_type": "troubleshooting",
    "created_by_id": "106",
    "reviewed_by_id": "80",
    "category": "payment_processing",
    "view_count": 349,
    "status": "draft",
    "created_at": "2023-11-26T09:35:23.028492",
    "updated_at": "2025-01-13T00:38:25.978271"
  },
  "60": {
    "article_id": "60",
    "incident_id": "114",
    "title": "How to Handle Gateway Unreachable",
    "article_type": "resolution_steps",
    "created_by_id": "70",
    "reviewed_by_id": "94",
    "category": "payment_processing",
    "view_count": 164,
    "status": "published",
    "created_at": "2024-03-31T16:51:24.433809",
    "updated_at": "2024-07-08T02:07:56.048292"
  },
  "61": {
    "article_id": "61",
    "incident_id": "116",
    "title": "How to Handle API Connection Failed",
    "article_type": "faq",
    "created_by_id": "70",
    "reviewed_by_id": null,
    "category": "api_integration",
    "view_count": 38,
    "status": "draft",
    "created_at": "2024-05-05T12:20:19.467730",
    "updated_at": "2024-12-14T11:22:53.182430"
  },
  "62": {
    "article_id": "62",
    "incident_id": "118",
    "title": "How to Handle Rate Limit Saturation",
    "article_type": "faq",
    "created_by_id": "70",
    "reviewed_by_id": null,
    "category": "api_integration",
    "view_count": 206,
    "status": "published",
    "created_at": "2025-05-22T22:14:06.105699",
    "updated_at": "2025-08-25T03:01:30.753226"
  },
  "63": {
    "article_id": "63",
    "incident_id": "120",
    "title": "How to Handle OAuth Token Rejected",
    "article_type": "resolution_steps",
    "created_by_id": "75",
    "reviewed_by_id": null,
    "category": "api_integration",
    "view_count": 101,
    "status": "archived",
    "created_at": "2025-06-06T12:08:23.551148",
    "updated_at": "2025-07-09T20:43:03.936253"
  },
  "64": {
    "article_id": "64",
    "incident_id": "121",
    "title": "How to Handle Primary Database Unavailable",
    "article_type": "resolution_steps",
    "created_by_id": "32",
    "reviewed_by_id": null,
    "category": "database_issues",
    "view_count": 199,
    "status": "draft",
    "created_at": "2025-04-10T19:32:26.630017",
    "updated_at": "2025-06-02T04:30:04.216474"
  },
  "65": {
    "article_id": "65",
    "incident_id": "122",
    "title": "How to Handle Primary Database Unavailable",
    "article_type": "resolution_steps",
    "created_by_id": "92",
    "reviewed_by_id": "41",
    "category": "database_issues",
    "view_count": 51,
    "status": "draft",
    "created_at": "2024-09-02T03:33:14.968963",
    "updated_at": "2024-10-16T08:40:33.213471"
  },
  "66": {
    "article_id": "66",
    "incident_id": "123",
    "title": "How to Handle Deadlocks Detected",
    "article_type": "faq",
    "created_by_id": "117",
    "reviewed_by_id": "25",
    "category": "database_issues",
    "view_count": 234,
    "status": "draft",
    "created_at": "2025-07-01T07:07:22.587369",
    "updated_at": "2025-08-13T10:00:07.490661"
  },
  "67": {
    "article_id": "67",
    "incident_id": "127",
    "title": "How to Handle Indexing Queue Backlog",
    "article_type": "resolution_steps",
    "created_by_id": "37",
    "reviewed_by_id": "11",
    "category": "monitoring_alerts",
    "view_count": 22,
    "status": "archived",
    "created_at": "2024-11-15T11:18:04.121092",
    "updated_at": "2025-06-05T20:44:20.402269"
  },
  "68": {
    "article_id": "68",
    "incident_id": "128",
    "title": "How to Handle Metrics Ingestion Delay",
    "article_type": "prevention_guide",
    "created_by_id": "70",
    "reviewed_by_id": "48",
    "category": "monitoring_alerts",
    "view_count": 391,
    "status": "archived",
    "created_at": "2024-06-02T01:06:56.380243",
    "updated_at": "2024-07-15T04:57:58.638321"
  },
  "69": {
    "article_id": "69",
    "incident_id": "129",
    "title": "How to Handle Indexing Queue Backlog",
    "article_type": "troubleshooting",
    "created_by_id": "85",
    "reviewed_by_id": null,
    "category": "monitoring_alerts",
    "view_count": 199,
    "status": "archived",
    "created_at": "2025-05-26T09:53:13.030128",
    "updated_at": "2025-07-03T19:00:40.495783"
  },
  "70": {
    "article_id": "70",
    "incident_id": "130",
    "title": "How to Handle Metrics Ingestion Delay",
    "article_type": "resolution_steps",
    "created_by_id": "12",
    "reviewed_by_id": "80",
    "category": "monitoring_alerts",
    "view_count": 286,
    "status": "published",
    "created_at": "2024-01-02T00:26:31.052746",
    "updated_at": "2024-07-30T15:05:37.352900"
  },
  "71": {
    "article_id": "71",
    "incident_id": "133",
    "title": "How to Handle DNS Resolution Failure for API",
    "article_type": "resolution_steps",
    "created_by_id": "106",
    "reviewed_by_id": null,
    "category": "api_integration",
    "view_count": 345,
    "status": "published",
    "created_at": "2025-04-20T11:43:52.358471",
    "updated_at": "2025-07-11T00:31:10.175936"
  },
  "72": {
    "article_id": "72",
    "incident_id": "134",
    "title": "How to Handle 5xx Error Spike on API",
    "article_type": "faq",
    "created_by_id": "43",
    "reviewed_by_id": null,
    "category": "api_integration",
    "view_count": 420,
    "status": "draft",
    "created_at": "2023-11-11T09:58:59.183605",
    "updated_at": "2024-06-21T03:05:58.755421"
  },
  "73": {
    "article_id": "73",
    "incident_id": "137",
    "title": "How to Handle Failover Did Not Trigger",
    "article_type": "resolution_steps",
    "created_by_id": "66",
    "reviewed_by_id": "39",
    "category": "database_issues",
    "view_count": 122,
    "status": "draft",
    "created_at": "2024-10-28T05:02:05.044628",
    "updated_at": "2024-12-29T23:36:30.736030"
  },
  "74": {
    "article_id": "74",
    "incident_id": "139",
    "title": "How to Handle Failover Did Not Trigger",
    "article_type": "prevention_guide",
    "created_by_id": "92",
    "reviewed_by_id": "72",
    "category": "database_issues",
    "view_count": 285,
    "status": "published",
    "created_at": "2025-08-29T18:10:30.831792",
    "updated_at": "2025-08-31T17:35:56.334210"
  },
  "75": {
    "article_id": "75",
    "incident_id": "140",
    "title": "How to Handle Write Conflicts Observed",
    "article_type": "resolution_steps",
    "created_by_id": "92",
    "reviewed_by_id": "21",
    "category": "database_issues",
    "view_count": 331,
    "status": "draft",
    "created_at": "2024-02-05T23:19:34.236056",
    "updated_at": "2024-06-27T19:15:24.893005"
  },
  "76": {
    "article_id": "76",
    "incident_id": "142",
    "title": "How to Handle Replication Lag High",
    "article_type": "troubleshooting",
    "created_by_id": "93",
    "reviewed_by_id": null,
    "category": "database_issues",
    "view_count": 24,
    "status": "archived",
    "created_at": "2025-03-31T02:56:02.605601",
    "updated_at": "2025-07-05T21:37:20.266786"
  },
  "77": {
    "article_id": "77",
    "incident_id": "143",
    "title": "How to Handle Replication Lag High",
    "article_type": "troubleshooting",
    "created_by_id": "72",
    "reviewed_by_id": "94",
    "category": "database_issues",
    "view_count": 124,
    "status": "draft",
    "created_at": "2025-08-05T22:38:49.716024",
    "updated_at": "2025-08-24T18:47:17.136235"
  },
  "78": {
    "article_id": "78",
    "incident_id": "144",
    "title": "How to Handle Write Conflicts Observed",
    "article_type": "prevention_guide",
    "created_by_id": "37",
    "reviewed_by_id": "116",
    "category": "database_issues",
    "view_count": 453,
    "status": "draft",
    "created_at": "2023-11-26T23:11:47.660133",
    "updated_at": "2025-02-12T06:10:19.596688"
  },
  "79": {
    "article_id": "79",
    "incident_id": "145",
    "title": "How to Handle Replication Lag High",
    "article_type": "resolution_steps",
    "created_by_id": "72",
    "reviewed_by_id": "84",
    "category": "database_issues",
    "view_count": 224,
    "status": "published",
    "created_at": "2024-06-08T21:48:34.376198",
    "updated_at": "2025-09-01T15:51:19.526090"
  },
  "80": {
    "article_id": "80",
    "incident_id": "146",
    "title": "How to Handle Deadlocks Detected",
    "article_type": "resolution_steps",
    "created_by_id": "9",
    "reviewed_by_id": null,
    "category": "database_issues",
    "view_count": 212,
    "status": "published",
    "created_at": "2024-11-18T10:38:19.781883",
    "updated_at": "2025-03-27T05:51:29.116943"
  },
  "81": {
    "article_id": "81",
    "incident_id": "147",
    "title": "How to Handle Indexing Queue Backlog",
    "article_type": "resolution_steps",
    "created_by_id": "93",
    "reviewed_by_id": null,
    "category": "monitoring_alerts",
    "view_count": 298,
    "status": "archived",
    "created_at": "2025-06-24T16:49:36.624038",
    "updated_at": "2025-07-11T05:44:05.200639"
  },
  "82": {
    "article_id": "82",
    "incident_id": null,
    "title": "General Guide: Ergonomic regional standardization",
    "article_type": "resolution_steps",
    "created_by_id": "75",
    "reviewed_by_id": "94",
    "category": "authentication_issues",
    "view_count": 87,
    "status": "archived",
    "created_at": "2025-02-08T02:59:07.569000",
    "updated_at": "2025-08-20T20:46:30.136123"
  },
  "83": {
    "article_id": "83",
    "incident_id": null,
    "title": "General Guide: Balanced next generation model",
    "article_type": "troubleshooting",
    "created_by_id": "118",
    "reviewed_by_id": null,
    "category": "system_outages",
    "view_count": 129,
    "status": "published",
    "created_at": "2025-01-13T07:48:46.385627",
    "updated_at": "2025-02-20T01:49:24.241158"
  },
  "84": {
    "article_id": "84",
    "incident_id": null,
    "title": "General Guide: Robust foreground access",
    "article_type": "resolution_steps",
    "created_by_id": "118",
    "reviewed_by_id": null,
    "category": "security_incidents",
    "view_count": 97,
    "status": "archived",
    "created_at": "2023-12-03T18:38:49.992442",
    "updated_at": "2025-04-22T10:40:43.233825"
  },
  "85": {
    "article_id": "85",
    "incident_id": null,
    "title": "General Guide: Polarized hybrid groupware",
    "article_type": "troubleshooting",
    "created_by_id": "82",
    "reviewed_by_id": "71",
    "category": "system_outages",
    "view_count": 22,
    "status": "published",
    "created_at": "2024-08-13T02:58:02.819742",
    "updated_at": "2025-06-27T06:22:01.537120"
  },
  "86": {
    "article_id": "86",
    "incident_id": null,
    "title": "General Guide: Managed well-modulated success",
    "article_type": "prevention_guide",
    "created_by_id": "89",
    "reviewed_by_id": "104",
    "category": "system_outages",
    "view_count": 362,
    "status": "draft",
    "created_at": "2024-01-04T01:12:25.492227",
    "updated_at": "2025-05-24T12:16:21.405054"
  },
  "87": {
    "article_id": "87",
    "incident_id": null,
    "title": "General Guide: Managed non-volatile concept",
    "article_type": "troubleshooting",
    "created_by_id": "12",
    "reviewed_by_id": "112",
    "category": "payment_processing",
    "view_count": 416,
    "status": "archived",
    "created_at": "2025-06-08T09:19:02.904451",
    "updated_at": "2025-08-30T23:31:13.873779"
  },
  "88": {
    "article_id": "88",
    "incident_id": null,
    "title": "General Guide: Vision-oriented human-resource matrices",
    "article_type": "troubleshooting",
    "created_by_id": "72",
    "reviewed_by_id": null,
    "category": "vendor_escalations",
    "view_count": 428,
    "status": "draft",
    "created_at": "2023-11-25T23:06:48.850139",
    "updated_at": "2025-07-23T02:20:43.621044"
  },
  "89": {
    "article_id": "89",
    "incident_id": null,
    "title": "General Guide: Visionary exuding firmware",
    "article_type": "troubleshooting",
    "created_by_id": "118",
    "reviewed_by_id": "21",
    "category": "system_outages",
    "view_count": 281,
    "status": "draft",
    "created_at": "2024-01-15T18:15:17.926961",
    "updated_at": "2025-02-16T02:33:59.476080"
  },
  "90": {
    "article_id": "90",
    "incident_id": null,
    "title": "General Guide: Total heuristic data-warehouse",
    "article_type": "prevention_guide",
    "created_by_id": "75",
    "reviewed_by_id": "94",
    "category": "user_management",
    "view_count": 127,
    "status": "archived",
    "created_at": "2025-07-14T22:33:21.100834",
    "updated_at": "2025-07-27T18:55:01.050519"
  },
  "91": {
    "article_id": "91",
    "incident_id": null,
    "title": "General Guide: Right-sized homogeneous database",
    "article_type": "resolution_steps",
    "created_by_id": "89",
    "reviewed_by_id": null,
    "category": "system_outages",
    "view_count": 428,
    "status": "archived",
    "created_at": "2025-01-04T23:48:09.048392",
    "updated_at": "2025-05-19T05:12:31.635480"
  },
  "92": {
    "article_id": "92",
    "incident_id": null,
    "title": "General Guide: Team-oriented methodical knowledgebase",
    "article_type": "resolution_steps",
    "created_by_id": "92",
    "reviewed_by_id": "97",
    "category": "security_incidents",
    "view_count": 64,
    "status": "published",
    "created_at": "2024-11-26T06:49:10.881278",
    "updated_at": "2025-04-30T18:27:58.218451"
  },
  "93": {
    "article_id": "93",
    "incident_id": null,
    "title": "General Guide: Mandatory 5thgeneration framework",
    "article_type": "faq",
    "created_by_id": "57",
    "reviewed_by_id": null,
    "category": "user_management",
    "view_count": 203,
    "status": "published",
    "created_at": "2024-05-30T12:46:54.226920",
    "updated_at": "2024-08-31T14:03:06.190766"
  },
  "94": {
    "article_id": "94",
    "incident_id": null,
    "title": "General Guide: Face-to-face foreground challenge",
    "article_type": "prevention_guide",
    "created_by_id": "82",
    "reviewed_by_id": "9",
    "category": "security_incidents",
    "view_count": 192,
    "status": "published",
    "created_at": "2024-09-01T08:42:39.121754",
    "updated_at": "2025-06-08T22:53:54.913612"
  },
  "95": {
    "article_id": "95",
    "incident_id": null,
    "title": "General Guide: Networked directional forecast",
    "article_type": "troubleshooting",
    "created_by_id": "106",
    "reviewed_by_id": null,
    "category": "data_synchronization",
    "view_count": 299,
    "status": "published",
    "created_at": "2023-09-17T21:37:55.029835",
    "updated_at": "2023-10-14T22:13:23.428727"
  },
  "96": {
    "article_id": "96",
    "incident_id": null,
    "title": "General Guide: Multi-channeled multi-state challenge",
    "article_type": "resolution_steps",
    "created_by_id": "112",
    "reviewed_by_id": "114",
    "category": "data_synchronization",
    "view_count": 76,
    "status": "draft",
    "created_at": "2024-08-30T03:13:13.388568",
    "updated_at": "2024-09-12T09:16:49.718773"
  },
  "97": {
    "article_id": "97",
    "incident_id": null,
    "title": "General Guide: Versatile coherent monitoring",
    "article_type": "prevention_guide",
    "created_by_id": "84",
    "reviewed_by_id": "58",
    "category": "api_integration",
    "view_count": 11,
    "status": "published",
    "created_at": "2025-05-09T20:44:50.971199",
    "updated_at": "2025-07-11T17:21:24.536821"
  },
  "98": {
    "article_id": "98",
    "incident_id": null,
    "title": "General Guide: Balanced asynchronous concept",
    "article_type": "prevention_guide",
    "created_by_id": "37",
    "reviewed_by_id": null,
    "category": "billing_issues",
    "view_count": 39,
    "status": "published",
    "created_at": "2025-07-20T01:20:16.578508",
    "updated_at": "2025-07-27T22:16:25.931412"
  },
  "99": {
    "article_id": "99",
    "incident_id": null,
    "title": "General Guide: Enterprise-wide national productivity",
    "article_type": "resolution_steps",
    "created_by_id": "11",
    "reviewed_by_id": null,
    "category": "user_management",
    "view_count": 367,
    "status": "published",
    "created_at": "2025-01-22T05:16:00.403251",
    "updated_at": "2025-04-22T08:35:46.577375"
  },
  "100": {
    "article_id": "100",
    "incident_id": null,
    "title": "General Guide: Synergistic full-range help-desk",
    "article_type": "prevention_guide",
    "created_by_id": "106",
    "reviewed_by_id": "4",
    "category": "backup_recovery",
    "view_count": 328,
    "status": "published",
    "created_at": "2024-06-03T23:27:07.511575",
    "updated_at": "2025-01-13T10:17:23.505575"
  }
}